deepsuite/README.md
deepsuite/__init__.py
deepsuite/registry.py
deepsuite/typing.py
deepsuite/callbacks/README.md
deepsuite/callbacks/__init__.py
deepsuite/callbacks/base.py
deepsuite/callbacks/embedding_logger.py
deepsuite/callbacks/kendryte.py
deepsuite/callbacks/onnx.py
deepsuite/callbacks/tensor_rt.py
deepsuite/callbacks/tflite.py
deepsuite/callbacks/torchscript.py
deepsuite/callbacks/tsne_laplace_callback.py
deepsuite/config/__init__.py
deepsuite/config/config_manager.py
deepsuite/heads/README.md
deepsuite/heads/__init__.py
deepsuite/heads/box.py
deepsuite/heads/centernet.py
deepsuite/heads/classification.py
deepsuite/heads/heatmap.py
deepsuite/heads/language_modeling.py
deepsuite/layers/README.md
deepsuite/layers/__init__.py
deepsuite/layers/bottleneck.py
deepsuite/layers/complex.py
deepsuite/layers/dft.py
deepsuite/layers/hermite.py
deepsuite/layers/laguerre.py
deepsuite/layers/mel.py
deepsuite/layers/moe.py
deepsuite/layers/attention/__init__.py
deepsuite/layers/attention/kv_compression.py
deepsuite/layers/attention/mla.py
deepsuite/layers/attention/rope.py
deepsuite/lightning_base/README.md
deepsuite/lightning_base/__init__.py
deepsuite/lightning_base/continual_learning_manager.py
deepsuite/lightning_base/module.py
deepsuite/lightning_base/trainer.py
deepsuite/lightning_base/dataset/__init__.py
deepsuite/lightning_base/dataset/audio_loader.py
deepsuite/lightning_base/dataset/base_loader.py
deepsuite/lightning_base/dataset/image_loader.py
deepsuite/lightning_base/dataset/text_loader.py
deepsuite/lightning_base/dataset/universal_set.py
deepsuite/loss/README.md
deepsuite/loss/__init__.py
deepsuite/loss/bbox.py
deepsuite/loss/centernet.py
deepsuite/loss/classification.py
deepsuite/loss/detection.py
deepsuite/loss/dfl.py
deepsuite/loss/distill.py
deepsuite/loss/focal.py
deepsuite/loss/heat.py
deepsuite/loss/keypoint.py
deepsuite/loss/language_modeling.py
deepsuite/loss/lwf.py
deepsuite/loss/mel.py
deepsuite/loss/rmse.py
deepsuite/loss/segmentation.py
deepsuite-1.0.8.dist-info/METADATA
deepsuite-1.0.8.dist-info/WHEEL
deepsuite-1.0.8.dist-info/licenses/LICENSE
deepsuite-1.0.8.dist-info/RECORD
